scieconlib/__init__.py
scieconlib/gametheory/__init__.py
scieconlib/gametheory/multi_agents/__init__.py
scieconlib/gametheory/multi_agents/agent.py
scieconlib/gametheory/multi_agents/model.py
scieconlib/gametheory/multi_agents/test.py
scieconlib/gametheory/multi_agents/examples/__init__.py
scieconlib/gametheory/multi_agents/examples/prisoner_dilemma.py
scieconlib/gametheory/multi_agents/examples/test.py
scieconlib/gametheory/multi_armed_bandit/__init__.py
scieconlib/gametheory/multi_armed_bandit/action.py
scieconlib/gametheory/multi_armed_bandit/agent.py
scieconlib/gametheory/multi_armed_bandit/distribution.py
scieconlib/gametheory/multi_armed_bandit/model.py
scieconlib-0.2.3.dist-info/METADATA
scieconlib-0.2.3.dist-info/WHEEL
scieconlib-0.2.3.dist-info/top_level.txt
scieconlib-0.2.3.dist-info/RECORD
