Metadata-Version: 2.1
Name: scieconlib
Version: 0.2.3
Summary: Tools for SciEcon projects
Home-page: UNKNOWN
Author: Crinstaniev
Author-email: zhuangzesen@gmail.com
License: UNKNOWN
Keywords: python,game theory,economy
Platform: UNKNOWN
Classifier: Development Status :: 3 - Alpha
Classifier: Intended Audience :: Education
Classifier: Programming Language :: Python :: 3
Classifier: Operating System :: MacOS :: MacOS X
Classifier: Operating System :: Microsoft :: Windows
Requires-Dist: plotly
Requires-Dist: numpy
Requires-Dist: pandas
Requires-Dist: scipy
Requires-Dist: tqdm
Requires-Dist: matplotlib
